CHANGELOG
LICENSE
MANIFEST.in
README.md
setup.py
python_potr.egg-info/PKG-INFO
python_potr.egg-info/SOURCES.txt
python_potr.egg-info/dependency_links.txt
python_potr.egg-info/requires.txt
python_potr.egg-info/top_level.txt
src/potr/__init__.py
src/potr/context.py
src/potr/crypt.py
src/potr/proto.py
src/potr/utils.py
src/potr/compatcrypto/__init__.py
src/potr/compatcrypto/common.py
src/potr/compatcrypto/pycrypto.py
src/tools/convertkey.py