Metadata-Version: 1.1
Name: python-potr
Version: 1.0.2
Summary: pure Python Off-The-Record encryption
Home-page: http://python-otr.pentabarf.de
Author: Kjell Braden
Author-email: afflux@pentabarf.de
License: LGPLv3+
Platform: any
Classifier: Development Status :: 5 - Production/Stable
Classifier: Intended Audience :: Developers
Classifier: License :: OSI Approved :: GNU Lesser General Public License v3 or later (LGPLv3+)
Classifier: Programming Language :: Python :: 2
Classifier: Programming Language :: Python :: 3
Classifier: Topic :: Communications :: Chat
Classifier: Topic :: Security :: Cryptography
